dgm_reactor_neutrino/__init__.py
dgm_reactor_neutrino/ee_to_enu.py
dgm_reactor_neutrino/ibd_xsec_vb_o1.py
dgm_reactor_neutrino/ibd_xsec_vb_o1_group.py
dgm_reactor_neutrino/inverse_square_law.py
dgm_reactor_neutrino/jacobian_d_enu_d_ee.py
dgm_reactor_neutrino/nue_survival_probability.py
dgm_reactor_neutrino-0.2.2.dist-info/licenses/LICENSE
dgm_reactor_neutrino-0.2.2.dist-info/METADATA
dgm_reactor_neutrino-0.2.2.dist-info/WHEEL
dgm_reactor_neutrino-0.2.2.dist-info/top_level.txt
dgm_reactor_neutrino-0.2.2.dist-info/RECORD
