Metadata-Version: 2.4
Name: dgm-reactor-neutrino
Version: 0.2.2
Summary: The package implements computational nodes for reactor electron antineutrino (oscillation) physics analysis for dag-modelling
Author-email: DAGModelling Team <dagflow@jinr.ru>
Maintainer-email: DAGModelling Team <dagflow@jinr.ru>
License-Expression: MIT
Project-URL: Bug Tracker, https://github.com/dagflow-team/dgm-reactor-neutrino/issues
Project-URL: DAGModelling Team, https://github.com/dagflow-team
Project-URL: documentation, https://github.com/dagflow-team/dgm-reactor-neutrino/wiki
Project-URL: homepage, https://github.com/dagflow-team/dgm-reactor-neutrino
Project-URL: repository, https://github.com/dagflow-team/dgm-reactor-neutrino
Classifier: Programming Language :: Python :: 3 :: Only
Classifier: Programming Language :: Python :: 3.11
Classifier: Programming Language :: Python :: 3.12
Classifier: Programming Language :: Python :: 3.13
Requires-Python: >=3.11
License-File: LICENSE
Requires-Dist: dag-modelling>=0.14.3
Requires-Dist: numba
Requires-Dist: scipy
Provides-Extra: test
Requires-Dist: dag-modelling[test]>=0.14.3; extra == "test"
Dynamic: license-file
